__init__.py
tte_depth.py
utils.py
tte_depth-1.0.0.dist-info/LICENSE
tte_depth-1.0.0.dist-info/METADATA
tte_depth-1.0.0.dist-info/WHEEL
tte_depth-1.0.0.dist-info/top_level.txt
tte_depth-1.0.0.dist-info/RECORD
