Metadata-Version: 2.1
Name: tte_depth
Version: 1.0.0
Summary: A package for implementing transformer-based text embedding depth
Author-email: pkseeg <parker@pkseeg.com>
Project-URL: Homepage, https://github.com/pkseeg/tte_depth
Project-URL: Bug Tracker, https://github.com/pkseeg/tte_depth/issues
Classifier: Programming Language :: Python :: 3
Classifier: License :: OSI Approved :: MIT License
Classifier: Operating System :: OS Independent
Requires-Python: >=3.7
License-File: LICENSE
